dictease/__init__.py
dictease/dictease.py
dictease-0.1.5.dist-info/LICENSE
dictease-0.1.5.dist-info/METADATA
dictease-0.1.5.dist-info/WHEEL
dictease-0.1.5.dist-info/top_level.txt
dictease-0.1.5.dist-info/RECORD
