Metadata-Version: 2.1
Name: dictease
Version: 0.1.5
Summary: A simple way to access the dictionary (nested dictionary).
Home-page: UNKNOWN
Author: ['S.Hasini', 'Deepak Das', 'Irfan Ahmed']
Author-email: ['hasinisingireddy2@gmail.com', 'dpk.ds3@gmail.com', 'mdirfanahmed12377@gmail.com']
License: UNKNOWN
Platform: UNKNOWN
Classifier: Programming Language :: Python :: 3
Classifier: License :: OSI Approved :: MIT License
Classifier: Operating System :: OS Independent
Requires-Python: >=3
License-File: LICENSE
